checkdoc/__init__.py
checkdoc/__init__.py~
checkdoc-0.2.0.dist-info/METADATA
checkdoc-0.2.0.dist-info/WHEEL
checkdoc-0.2.0.dist-info/entry_points.txt
checkdoc-0.2.0.dist-info/RECORD
