Metadata-Version: 2.4
Name: checkdoc
Version: 0.2.0
Summary: Scan a word document for phrases.
Requires-Python: >=3.13
Requires-Dist: python-docx>=1.2.0
